im282a.py
im282a-3.0.1.dist-info/LICENSE
im282a-3.0.1.dist-info/METADATA
im282a-3.0.1.dist-info/WHEEL
im282a-3.0.1.dist-info/top_level.txt
im282a-3.0.1.dist-info/RECORD
