Metadata-Version: 2.1
Name: im282a
Version: 3.0.1
Summary: Library for the iM282A radio transceiver module
Home-page: https://github.com/cubic3d/im282a
Author: Waldemar Faist
Author-email: cubic@coldice.net
License: MIT
Project-URL: Bug Tracker, https://github.com/cubic3d/im282a/issues
Platform: UNKNOWN
Classifier: Programming Language :: Python :: 3
Classifier: License :: OSI Approved :: MIT License
Classifier: Operating System :: OS Independent
Requires-Python: >=3.7
License-File: LICENSE
Requires-Dist: sliplib (>=0.6.2)
Requires-Dist: crccheck (>=1.0)
Requires-Dist: pyserial (>=3.5)
